{
  "profile": "A",
  "load_time_s": 1.9637108329916373,
  "peak_memory_after_load_mb": 1548.1368713378906,
  "prefill_plus_first_token_s": 5.4340392500162125,
  "prefill_step_size": 64,
  "decode_tok_per_s": 12.368960337695725,
  "decode_split_point_tokens": null,
  "decode_first_half_tok_per_s": null,
  "decode_second_half_tok_per_s": null,
  "peak_memory_mb": 5807.298397064209,
  "kv_cache_type": "isoquant",
  "expert_offload": true,
  "use_predictor": true,
  "use_dedekimi_observer": true,
  "task_expert_cliques": true,
  "expert_cache": {
    "hits": 33668,
    "misses": 3585,
    "evictions": 69217,
    "hit_rate": 0.9037661396397606,
    "prefill_hits": 3188,
    "prefill_misses": 3105,
    "prefill_hit_rate": 0.5065946289528047,
    "decode_hits": 30480,
    "decode_misses": 480,
    "decode_hit_rate": 0.9844961240310077,
    "avg_load_ms": 0.01382762975832295,
    "resident_slots": 128,
    "prefill_gather_calls": 240,
    "decode_gather_calls": 3870,
    "prefetch_requests": 65776,
    "prefetch_already_cached": 0
  },
  "warm_second_pass": false,
  "warm_pass_decode_tok_per_s": null,
  "warm_pass_peak_memory_mb": null,
  "warm_pass_expert_cache": {}
}